rawtypes/__init__.py
rawtypes/__main__.py
rawtypes/_version.py
rawtypes/vcenv.py
rawtypes/clang/__init__.py
rawtypes/clang/cindex.py
rawtypes/clang/enumerations.py
rawtypes/clang_util/__init__.py
rawtypes/clang_util/generate_cindex_stub.py
rawtypes/generator/__init__.py
rawtypes/generator/cpp_writer.py
rawtypes/generator/generator_base.py
rawtypes/generator/py_writer.py
rawtypes/generator/python_generator.py
rawtypes/generator/zig_generator.py
rawtypes/generator/templates/ctypes_structure.py
rawtypes/generator/templates/impl.cpp
rawtypes/generator/templates/module.cpp
rawtypes/generator/templates/pycfunc.cpp
rawtypes/generator/templates/rawtypes.h
rawtypes/interpreted_types/__init__.py
rawtypes/interpreted_types/basetype.py
rawtypes/interpreted_types/definition.py
rawtypes/interpreted_types/function_types.py
rawtypes/interpreted_types/pointer_types.py
rawtypes/interpreted_types/primitive_types.py
rawtypes/interpreted_types/string_types.py
rawtypes/interpreted_types/type_manager.py
rawtypes/interpreted_types/wrap_types.py
rawtypes/parser/__init__.py
rawtypes/parser/enum_cursor.py
rawtypes/parser/function_cursor.py
rawtypes/parser/header.py
rawtypes/parser/parser.py
rawtypes/parser/struct_cursor.py
rawtypes/parser/type_context.py
rawtypes/parser/typedef_cursor.py
rawtypes-1.8.0.dist-info/LICENSE
rawtypes-1.8.0.dist-info/METADATA
rawtypes-1.8.0.dist-info/WHEEL
rawtypes-1.8.0.dist-info/top_level.txt
rawtypes-1.8.0.dist-info/RECORD
