Metadata-Version: 2.1
Name: rawtypes
Version: 1.8.0
Summary: A code generator using libclang for a python extension.
Author: ousttrue
Project-URL: Documentation, https://ousttrue.github.io/rawtypes/
Project-URL: Source, https://github.com/ousttrue/rawtypes
Classifier: Development Status :: 3 - Alpha
Classifier: Intended Audience :: Developers
Classifier: Topic :: Software Development :: Build Tools
Classifier: License :: OSI Approved :: MIT License
Classifier: Programming Language :: Python :: 3.10
License-File: LICENSE
Requires-Dist: Jinja2
